crackle_api_helpers/__init__.py
crackle_api_helpers/api_wrapper.py
crackle_api_helpers/auth_key_missing_error.py
crackle_api_helpers/session.py
crackle_api_helpers/tests.py
crackle_api_helpers/authentication/__init__.py
crackle_api_helpers/authentication/authentication.py
crackle_api_helpers/authentication/authentication_helpers.py
crackle_api_helpers-1.19.dist-info/METADATA
crackle_api_helpers-1.19.dist-info/RECORD
crackle_api_helpers-1.19.dist-info/WHEEL
crackle_api_helpers-1.19.dist-info/top_level.txt
crackle_api_helpers-1.19.dist-info/zip-safe
