Metadata-Version: 2.1
Name: crackle-api-helpers
Version: 1.19
Summary: crackle api helpers
Home-page: https://github.com/CrackleEngineering/crackle_api_helpers
Author: Clark Mckenzie
Author-email: clarkmckenzie@googlemail.com
License: MIT
Platform: UNKNOWN
Requires-Dist: requests
Requires-Dist: urllib3
